djangomodelimport/__init__.py
djangomodelimport/caches.py
djangomodelimport/core.py
djangomodelimport/fields.py
djangomodelimport/formclassbuilder.py
djangomodelimport/forms.py
djangomodelimport/loaders.py
djangomodelimport/magic.py
djangomodelimport/parsers.py
djangomodelimport/resultset.py
djangomodelimport/utils.py
djangomodelimport/widgets.py
django_model_import-0.7.7.dist-info/METADATA
django_model_import-0.7.7.dist-info/WHEEL
django_model_import-0.7.7.dist-info/RECORD
