Metadata-Version: 2.3
Name: django-model-import
Version: 0.7.7
Summary: A Django library for importing CSVs and other structured data quickly using Django's ModelForm for validation and deserialisation into an instance.
License: MIT
Author: Aidan Lister
Author-email: aidan@uptickhq.com
Requires-Python: >=3.10,<4.0
Classifier: License :: OSI Approved :: MIT License
Classifier: Programming Language :: Python :: 3
Classifier: Programming Language :: Python :: 3.10
Classifier: Programming Language :: Python :: 3.11
Classifier: Programming Language :: Python :: 3.12
Classifier: Programming Language :: Python :: 3.13
Requires-Dist: django (>=3.2.0,<6.0.0)
Requires-Dist: python-dateutil (>=2.7.0,<3.0.0)
Requires-Dist: tablib (>=3.0.0,<4.0.0)
Project-URL: Documentation, https://github.com/uptick/django-model-import/tree/master/tests/djangoexample
Project-URL: Homepage, https://github.com/uptick/django-model-import
Project-URL: Repository, https://github.com/uptick/django-model-import
